ft_agui/__init__.py
ft_agui/core.py
ft_agui/layouts.py
ft_agui/patches.py
ft_agui/styles.py
ft_agui-0.1.0.dist-info/METADATA
ft_agui-0.1.0.dist-info/WHEEL
ft_agui-0.1.0.dist-info/RECORD
