Metadata-Version: 2.4
Name: ft-agui
Version: 0.1.0
Summary: Easy AGUI integration for FastHTML applications - as simple as pydantic-ai's to_web()!
Project-URL: Homepage, https://github.com/Novia-RDI-Seafaring/ft-ag-ui
Project-URL: Repository, https://github.com/Novia-RDI-Seafaring/ft-ag-ui
Project-URL: Documentation, https://github.com/Novia-RDI-Seafaring/ft-ag-ui#readme
Project-URL: Bug Reports, https://github.com/Novia-RDI-Seafaring/ft-ag-ui/issues
Author-email: Christoffer Björkskog <christoffer.bjorkskog@novia.fi>
License-Expression: MIT
Keywords: agui,chat,fasthtml,pydantic-ai,ui,websocket
Classifier: Development Status :: 4 - Beta
Classifier: Framework :: FastAPI
Classifier: Intended Audience :: Developers
Classifier: License :: OSI Approved :: MIT License
Classifier: Programming Language :: Python :: 3
Classifier: Programming Language :: Python :: 3.11
Classifier: Programming Language :: Python :: 3.12
Classifier: Topic :: Internet :: WWW/HTTP :: Dynamic Content
Classifier: Topic :: Software Development :: Libraries :: Python Modules
Classifier: Topic :: Software Development :: User Interfaces
Requires-Python: >=3.11
Requires-Dist: ag-ui-core>=0.1.0
Requires-Dist: pydantic-ai>=1.34.0
Requires-Dist: pydantic>=2.12.5
Requires-Dist: python-fasthtml>=0.12.36
